MANIFEST.in
requirements.txt
setup.py
emokit/__init__.py
emokit/battery.py
emokit/decrypter.py
emokit/emotiv.py
emokit/output.py
emokit/packet.py
emokit/python_queue.py
emokit/reader.py
emokit/sensors.py
emokit/tasks.py
emokit/util.py
emokit/writer.py
emokit.egg-info/PKG-INFO
emokit.egg-info/SOURCES.txt
emokit.egg-info/dependency_links.txt
emokit.egg-info/not-zip-safe
emokit.egg-info/requires.txt
emokit.egg-info/top_level.txt
tests/test_emokit.py