Metadata-Version: 1.1
Name: emokit
Version: 0.0.8
Summary: emotiv epoc eeg headset sdk
Home-page: https://github.com/openyou/emokit
Author: Bill Schumacher
Author-email: bill@servernet.co
License: Public Domain, SEE LICENSE
Platform: any
Classifier: Operating System :: OS Independent
Classifier: Programming Language :: Python
